aiq/meta/pypi.md
aiq/plugins/phoenix/__init__.py
aiq/plugins/phoenix/phoenix_exporter.py
aiq/plugins/phoenix/register.py
aiq/plugins/phoenix/mixin/__init__.py
aiq/plugins/phoenix/mixin/phoenix_mixin.py
aiqtoolkit_phoenix-1.2.0a20250806.dist-info/METADATA
aiqtoolkit_phoenix-1.2.0a20250806.dist-info/WHEEL
aiqtoolkit_phoenix-1.2.0a20250806.dist-info/entry_points.txt
aiqtoolkit_phoenix-1.2.0a20250806.dist-info/top_level.txt
aiqtoolkit_phoenix-1.2.0a20250806.dist-info/RECORD
