Metadata-Version: 2.4
Name: aiqtoolkit-phoenix
Version: 1.2.0a20250806
Summary: Subpackage for Arize Phoenix integration in AIQtoolkit
Keywords: ai,observability,phoenix,arize
Classifier: Programming Language :: Python
Requires-Python: <3.13,>=3.11
Requires-Dist: aiqtoolkit[opentelemetry]==v1.2.0a20250806
Requires-Dist: arize-phoenix~=6.1
